setup.cfg
setup.py
as/__init__.py
as.recipe.frozenpkg.egg-info/PKG-INFO
as.recipe.frozenpkg.egg-info/SOURCES.txt
as.recipe.frozenpkg.egg-info/dependency_links.txt
as.recipe.frozenpkg.egg-info/entry_points.txt
as.recipe.frozenpkg.egg-info/namespace_packages.txt
as.recipe.frozenpkg.egg-info/not-zip-safe
as.recipe.frozenpkg.egg-info/requires.txt
as.recipe.frozenpkg.egg-info/top_level.txt
as/recipe/__init__.py
as/recipe/frozenpkg/__init__.py
as/recipe/frozenpkg/frozen.py
as/recipe/frozenpkg/frozenrpm.py
as/recipe/frozenpkg/frozentgz.py