Metadata-Version: 1.1
Name: as.recipe.frozenpkg
Version: 0.2.20
Summary: ZC Buildout recipe for freezing buildouts in RPM's, tar.gz's, etc
Home-page: UNKNOWN
Author: Alvaro Saurin
Author-email: name dot surname at gmail.com
License: GPL
Keywords: buildout recipe
Platform: UNKNOWN
Classifier: Framework :: Buildout
Classifier: Intended Audience :: Developers
Classifier: Topic :: Software Development :: Build Tools
Classifier: Topic :: Software Development :: Libraries :: Python Modules
Classifier: License :: OSI Approved :: GNU General Public License (GPL)
